AUTHORS
CHANGELOG
INSTALL
LICENSE.txt
MANIFEST.in
README
setup.py
GooeyPy.egg-info/PKG-INFO
GooeyPy.egg-info/SOURCES.txt
GooeyPy.egg-info/dependency_links.txt
GooeyPy.egg-info/requires.txt
GooeyPy.egg-info/top_level.txt
docs/__init__.py
docs/box.html
docs/build.py
docs/button.html
docs/container.html
docs/effects.html
docs/image.html
docs/index.html
docs/input.html
docs/label.html
docs/selectbox.html
docs/slider.html
docs/styleset.html
docs/textblock.html
docs/widget.html
docs/skin/index.html
docs/skin/logo.png
docs/skin/logo.svg
docs/skin/style.css
examples/__init__.py
examples/crab.gif
examples/example1.py
examples/example2.py
examples/example3.py
examples/image.png
gooeypy/__init__.py
gooeypy/box.py
gooeypy/button.py
gooeypy/const.py
gooeypy/container.py
gooeypy/descriptor.py
gooeypy/effects.py
gooeypy/image.py
gooeypy/input.py
gooeypy/label.py
gooeypy/selectbox.py
gooeypy/slider.py
gooeypy/styleset.py
gooeypy/textblock.py
gooeypy/widget.py
gooeypy/data/themes/default/.directory
gooeypy/data/themes/default/Vera.ttf
gooeypy/data/themes/default/bg.png
gooeypy/data/themes/default/button.png
gooeypy/data/themes/default/button.xcf
gooeypy/data/themes/default/button_down.png
gooeypy/data/themes/default/button_down_trans.png
gooeypy/data/themes/default/button_focused.png
gooeypy/data/themes/default/button_focused_trans.png
gooeypy/data/themes/default/button_hover.png
gooeypy/data/themes/default/button_hover_trans.png
gooeypy/data/themes/default/button_trans.png
gooeypy/data/themes/default/input.png
gooeypy/data/themes/default/input_focused.png
gooeypy/data/themes/default/slider.png
gooeypy/data/themes/default/theme.style