Metadata-Version: 1.0
Name: GooeyPy
Version: 0.2
Summary: A fast, flexible, and cool looking GUI for pygame.
Home-page: http://joey101.net/gooeypy/
Author: Joey Marshall
Author-email: web@joey101.net
License: LGPL
Keywords: gooeypy gui pygame
Platform: any
